MANIFEST.in
README.txt
setup.cfg
setup.py
docs/HISTORY.txt
docs/INSTALL.txt
docs/LICENSE.GPL
docs/LICENSE.txt
plonetheme/__init__.py
plonetheme.porseleinplaats.egg-info/PKG-INFO
plonetheme.porseleinplaats.egg-info/SOURCES.txt
plonetheme.porseleinplaats.egg-info/dependency_links.txt
plonetheme.porseleinplaats.egg-info/entry_points.txt
plonetheme.porseleinplaats.egg-info/namespace_packages.txt
plonetheme.porseleinplaats.egg-info/not-zip-safe
plonetheme.porseleinplaats.egg-info/paster_plugins.txt
plonetheme.porseleinplaats.egg-info/requires.txt
plonetheme.porseleinplaats.egg-info/top_level.txt
plonetheme/porseleinplaats/__init__.py
plonetheme/porseleinplaats/configure.zcml
plonetheme/porseleinplaats/events.py
plonetheme/porseleinplaats/profiles.zcml
plonetheme/porseleinplaats/setuphandlers.py
plonetheme/porseleinplaats/skins.zcml
plonetheme/porseleinplaats/tests.py
plonetheme/porseleinplaats/version.txt
plonetheme/porseleinplaats/browser/__init__.py
plonetheme/porseleinplaats/browser/add_porselein.pt
plonetheme/porseleinplaats/browser/app.py
plonetheme/porseleinplaats/browser/app_view_home.pt
plonetheme/porseleinplaats/browser/app_view_object.pt
plonetheme/porseleinplaats/browser/app_view_vitrine.pt
plonetheme/porseleinplaats/browser/app_view_vitrine_bak.pt
plonetheme/porseleinplaats/browser/app_view_vitrines_list.pt
plonetheme/porseleinplaats/browser/collection.pt
plonetheme/porseleinplaats/browser/configure.zcml
plonetheme/porseleinplaats/browser/folder_slideshow_view.pt
plonetheme/porseleinplaats/browser/folder_slideshow_view.py
plonetheme/porseleinplaats/browser/folder_view.pt
plonetheme/porseleinplaats/browser/folder_view.py
plonetheme/porseleinplaats/browser/interfaces.py
plonetheme/porseleinplaats/browser/manage_home.pt
plonetheme/porseleinplaats/browser/manage_sidebar.pt
plonetheme/porseleinplaats/browser/members_view.pt
plonetheme/porseleinplaats/browser/members_view.py
plonetheme/porseleinplaats/browser/next_prev_view.py
plonetheme/porseleinplaats/browser/next_view.pt
plonetheme/porseleinplaats/browser/object_view.pt
plonetheme/porseleinplaats/browser/object_view.py
plonetheme/porseleinplaats/browser/portlet_view.pt
plonetheme/porseleinplaats/browser/portlet_view.py
plonetheme/porseleinplaats/browser/prev_view.pt
plonetheme/porseleinplaats/browser/relateditems.pt
plonetheme/porseleinplaats/browser/relateditems.py
plonetheme/porseleinplaats/browser/searchview.py
plonetheme/porseleinplaats/browser/sidebar.pt
