Metadata-Version: 1.0
Name: plonetheme.porseleinplaats
Version: 0.50
Summary: An installable theme for Plone 3
Home-page: http://svn.plone.org/svn/collective/
Author: David Jonas
Author-email: davidjonasdesign@gmail.com
License: GPL
Keywords: web zope plone theme
Platform: UNKNOWN
Classifier: Framework :: Plone
Classifier: Programming Language :: Python
